tiffit/__init__.py
tiffit/subparser_play.py
tiffit/subparser_play2.py
tiffit/tiffit.py
tiffit-0.1.0.dist-info/METADATA
tiffit-0.1.0.dist-info/WHEEL
tiffit-0.1.0.dist-info/entry_points.txt
tiffit-0.1.0.dist-info/top_level.txt
tiffit-0.1.0.dist-info/RECORD
