Metadata-Version: 2.1
Name: tiffit
Version: 0.1.0
Summary: Lightweight tiff utilities
Home-page: https://github.com/EricThomson/tiffit
Author: Eric Thomson
Author-email: thomson.eric@gmail.com
License: MIT
Platform: UNKNOWN
Requires-Dist: tifffile
Requires-Dist: tifftools
